README.md
setup.py
simple_i18n/I18n.py
simple_i18n/__init__.py
simple_i18n.egg-info/PKG-INFO
simple_i18n.egg-info/SOURCES.txt
simple_i18n.egg-info/dependency_links.txt
simple_i18n.egg-info/requires.txt
simple_i18n.egg-info/top_level.txt
simple_i18n.egg-info/zip-safe