Metadata-Version: 2.1
Name: simple-i18n
Version: 0.1.2
Home-page: https://github.com/iDkGK/simple-i18n
Author: iDkGK
Author-email: 1444807655@qq.com
Maintainer: iDkGK
Maintainer-email: 1444807655@qq.com
License: MIT
Keywords: i18n,gettext,translation
Platform: MacOS X
Platform: Windows
Platform: Linux
Classifier: Development Status :: 4 - Beta
Classifier: Intended Audience :: Developers
Classifier: License :: OSI Approved :: Python Software Foundation License
Classifier: Operating System :: MacOS :: MacOS X
Classifier: Operating System :: Microsoft :: Windows
Classifier: Operating System :: POSIX :: Linux
Classifier: Programming Language :: Python
Classifier: Topic :: Utilities
Classifier: Topic :: Software Development :: Internationalization
